setup.py
src/WxToolsLujx/WxToolsLujx.py
src/WxToolsLujx/__init__.py
src/WxToolsLujx.egg-info/PKG-INFO
src/WxToolsLujx.egg-info/SOURCES.txt
src/WxToolsLujx.egg-info/dependency_links.txt
src/WxToolsLujx.egg-info/top_level.txt